setup.py
fovbpsk/__init__.py
fovbpsk/__main__.py
fovbpsk/alsa.py
fovbpsk/async_reader.py
fovbpsk/audio.py
fovbpsk/calib.py
fovbpsk/common.py
fovbpsk/config.py
fovbpsk/detect.py
fovbpsk/dsp.py
fovbpsk/equalizer.py
fovbpsk/framing.py
fovbpsk/levinson.py
fovbpsk/main.py
fovbpsk/recv.py
fovbpsk/sampling.py
fovbpsk/send.py
fovbpsk/stream.py
fovbpsk.egg-info/PKG-INFO
fovbpsk.egg-info/SOURCES.txt
fovbpsk.egg-info/dependency_links.txt
fovbpsk.egg-info/requires.txt
fovbpsk.egg-info/top_level.txt
fovbpsk/tests/__init__.py
fovbpsk/tests/test_alsa.py
fovbpsk/tests/test_async_reader.py
fovbpsk/tests/test_audio.py
fovbpsk/tests/test_calib.py
fovbpsk/tests/test_common.py
fovbpsk/tests/test_configs.py
fovbpsk/tests/test_detect.py
fovbpsk/tests/test_dsp.py
fovbpsk/tests/test_equalizer.py
fovbpsk/tests/test_framing.py
fovbpsk/tests/test_sampling.py
fovbpsk/tests/test_stream.py
fovbpsk/tests/test_transfer.py
fovbpsk/tests/utils.py