Metadata-Version: 2.2
Name: fovbpsk
Version: 1.0.0
Summary: FOVBPS-Kkutina
Home-page: https://github.com/Cache-Cloud/FOVBPSK-Kutina
Author: Kutina
Author-email: wang@kutina.cn
License: MIT Licence
Keywords: pip,Kutina
Platform: any
Requires-Dist: setuptools
Requires-Dist: setuptools-scm
Dynamic: author
Dynamic: author-email
Dynamic: description
Dynamic: home-page
Dynamic: keywords
Dynamic: license
Dynamic: platform
Dynamic: requires-dist
Dynamic: summary
